[{"id": "e", "eid": "140962", "mot": "'piston'"}, {"id": "e", "eid": "237", "mot": "'objet'"}, {"id": "e", "eid": "246870", "mot": "'objet&gt"}, {"id": "e", "eid": "216183", "mot": "'pi\u00e8ce m\u00e9canique'"}, {"id": "e", "eid": "144032", "mot": "'cylindre'"}, {"id": "e", "eid": "106265", "mot": "'appareil'"}, {"id": "e", "eid": "117604", "mot": "'m\u00e9canisme'"}, {"id": "e", "eid": "25856", "mot": "'valve'"}, {"id": "e", "eid": "139768", "mot": "'art\u00e9fact'"}, {"id": "e", "eid": "96851", "mot": "'pi\u00e8ce'"}, {"id": "e", "eid": "316850", "mot": "'entit\u00e9 physique'"}, {"id": "e", "eid": "67368", "mot": "'m\u00e9canique'"}, {"id": "e", "eid": "105716", "mot": "'tuyau'"}, {"id": "e", "eid": "134899", "mot": "'tube'"}, {"id": "e", "eid": "215393", "mot": "'tube&gt"}, {"id": "e", "eid": "20795", "mot": "'tuba'"}, {"id": "e", "eid": "64227", "mot": "'anomalie'"}, {"id": "r", "r": "sortante", "rid": "3086178", "node1": "140962", "node2": "237", "type": "6", "w": "124"}, {"id": "r", "r": "sortante", "rid": "3086177", "node1": "140962", "node2": "246870", "type": "6", "w": "124"}, {"id": "r", "r": "sortante", "rid": "9923259", "node1": "140962", "node2": "216183", "type": "6", "w": "49"}, {"id": "r", "r": "sortante", "rid": "97347512", "node1": "140962", "node2": "144032", "type": "6", "w": "45"}, {"id": "r", "r": "sortante", "rid": "57568996", "node1": "140962", "node2": "106265", "type": "6", "w": "39"}, {"id": "r", "r": "sortante", "rid": "110119219", "node1": "140962", "node2": "117604", "type": "6", "w": "31"}, {"id": "r", "r": "sortante", "rid": "82790794", "node1": "140962", "node2": "25856", "type": "6", "w": "28"}, {"id": "r", "r": "sortante", "rid": "427594923", "node1": "140962", "node2": "139768", "type": "6", "w": "26"}, {"id": "r", "r": "sortante", "rid": "214461913", "node1": "140962", "node2": "96851", "type": "6", "w": "26"}, {"id": "r", "r": "sortante", "rid": "371178508", "node1": "140962", "node2": "316850", "type": "6", "w": "25"}, {"id": "r", "r": "sortante", "rid": "4980439", "node1": "140962", "node2": "67368", "type": "6", "w": "5"}, {"id": "r", "r": "sortante", "rid": "3086175", "node1": "140962", "node2": "105716", "type": "6", "w": "0"}, {"id": "r", "r": "sortante", "rid": "3086179", "node1": "140962", "node2": "134899", "type": "6", "w": "-1"}, {"id": "r", "r": "sortante", "rid": "3086173", "node1": "140962", "node2": "215393", "type": "6", "w": "-1"}, {"id": "r", "r": "sortante", "rid": "3086166", "node1": "140962", "node2": "20795", "type": "6", "w": "-1"}, {"id": "r", "r": "sortante", "rid": "79958667", "node1": "140962", "node2": "64227", "type": "6", "w": "-27"}]